py_ads_client-0.0.7.dist-info/METADATA
py_ads_client-0.0.7.dist-info/WHEEL
py_ads_client-0.0.7.dist-info/licenses/LICENSE
py_ads_client/__init__.py
py_ads_client/ads_client.py
py_ads_client/ads_symbol.py
py_ads_client/ams/__init__.py
py_ads_client/ams/ads_add_device_notification.py
py_ads_client/ams/ads_delete_device_notification.py
py_ads_client/ams/ads_device_notification.py
py_ads_client/ams/ads_read.py
py_ads_client/ams/ads_read_device_info.py
py_ads_client/ams/ads_read_state.py
py_ads_client/ams/ads_read_write.py
py_ads_client/ams/ads_write.py
py_ads_client/ams/ads_write_control.py
py_ads_client/ams/ams_header.py
py_ads_client/ams/tests/__init__.py
py_ads_client/ams/tests/test_ads_add_device_notification.py
py_ads_client/ams/tests/test_ads_delete_device_notification.py
py_ads_client/ams/tests/test_ads_device_notification.py
py_ads_client/ams/tests/test_ads_read.py
py_ads_client/ams/tests/test_ads_read_device_info.py
py_ads_client/ams/tests/test_ads_read_state.py
py_ads_client/ams/tests/test_ads_read_write.py
py_ads_client/ams/tests/test_ads_write.py
py_ads_client/ams/tests/test_ads_write_control.py
py_ads_client/ams/tests/test_ams_header.py
py_ads_client/constants/__init__.py
py_ads_client/constants/ads_state.py
py_ads_client/constants/command_id.py
py_ads_client/constants/encoding.py
py_ads_client/constants/index_group.py
py_ads_client/constants/return_code.py
py_ads_client/constants/state_flag.py
py_ads_client/constants/transmission_mode.py
py_ads_client/helpers/__init__.py
py_ads_client/helpers/decode_ams_payload.py
py_ads_client/helpers/encode_ams_payload.py
py_ads_client/helpers/tests/__init__.py
py_ads_client/helpers/tests/test_complex_payload.py
py_ads_client/helpers/tests/test_simple_array_payload.py
py_ads_client/helpers/tests/test_time_date_payload.py
py_ads_client/py.typed
py_ads_client/tests/__init__.py
py_ads_client/tests/test_ads_client.py
py_ads_client/tests/test_ads_symbol.py
py_ads_client/tests/test_types.py
py_ads_client/types.py
py_ads_client/version.py
py_ads_client-0.0.7.dist-info/RECORD
