Metadata-Version: 2.1
Name: py-ads-client
Version: 0.0.7
Summary: TwinCAT ADS client for Python.
Keywords: TwinCAT,ADS
Author-Email: Yanxi Wang <wangyanxi@users.noreply.github.com>
License:                                  Apache License
Classifier: Development Status :: 3 - Alpha
Classifier: Intended Audience :: Developers
Classifier: Programming Language :: Python :: 3
Classifier: Programming Language :: Python :: 3.8
Classifier: Programming Language :: Python :: 3.9
Classifier: Programming Language :: Python :: 3.10
Classifier: Programming Language :: Python :: 3.11
Classifier: Programming Language :: Python :: 3.12
Classifier: Typing :: Typed
Project-URL: Github, https://github.com/wangyanxi/py-ads-client
Project-URL: Issues, https://github.com/wangyanxi/py-ads-client/issues
Project-URL: Documentation, https://py-ads-client.readthedocs.io
Requires-Python: >=3.8
Requires-Dist: typing-extensions~=4.9
